shry/__init__.py
shry/_version.py
shry/const.py
shry/core.py
shry/main.py
shry/script.py
shry-1.1.8.dist-info/LICENSE
shry-1.1.8.dist-info/METADATA
shry-1.1.8.dist-info/WHEEL
shry-1.1.8.dist-info/entry_points.txt
shry-1.1.8.dist-info/top_level.txt
shry-1.1.8.dist-info/RECORD
