Metadata-Version: 2.2
Name: SHRY
Version: 1.1.8
Home-page: https://github.com/shry-project/SHRY
Author: Genki Prayogo, Kosuke Nakano
Author-email: g.prayogo@icloud.com, kousuke_1123@icloud.com
Project-URL: Bug tracker, https://github.com/shry-project/SHRY/issues
Project-URL: Documentations, https://shry.readthedocs.io/en/latest/
Classifier: Intended Audience :: Science/Research
Classifier: Programming Language :: Python
Classifier: Programming Language :: Python :: 3.8
Classifier: Programming Language :: Python :: 3.9
Classifier: Programming Language :: Python :: 3.10
Classifier: Programming Language :: Python :: 3.11
Classifier: Programming Language :: Python :: 3.12
Classifier: License :: OSI Approved :: MIT License
Classifier: Operating System :: OS Independent
Classifier: Topic :: Scientific/Engineering :: Mathematics
Classifier: Topic :: Scientific/Engineering :: Physics
Requires-Python: >=3.7.2
License-File: LICENSE
Requires-Dist: numpy<2.0.0,>=1.17
Requires-Dist: pandas>=1.3.0
Requires-Dist: pymatgen<=2023.10.4,>=2019.1.13
Requires-Dist: scipy>=1.4.1
Requires-Dist: sympy>=1.5.1
Requires-Dist: tqdm>=4.60.0
Requires-Dist: pytest>=3.0.0
Requires-Dist: setuptools_scm>=7.0.5
Requires-Dist: xlrd>=1.0.0
Requires-Dist: spglib<=2.4.0
